psordinal/__init__.py
psordinal/main.py
psordinal/module.py
psordinal-0.1.dist-info/METADATA
psordinal-0.1.dist-info/WHEEL
psordinal-0.1.dist-info/entry_points.txt
psordinal-0.1.dist-info/top_level.txt
psordinal-0.1.dist-info/RECORD
