Metadata-Version: 2.1
Name: psordinal
Version: 0.1
Summary: OrdinalClassifier package
Author: Paul77ms
